{"generated_at": "2026-07-19 06:19 UTC", "months": ["2025-12", "2026-01", "2026-02", "2026-03", "2026-04", "2026-05", "2026-06", "2026-07"], "counts": {"episodes": 116, "recommendations": 650, "scored": 264}, "latest": {"date": "2026-07-17", "title": "Summary — Business Breakfast, 17 July 2026 (TV5 Money)", "stem": "2026-07-17__Business_Breakfast_StockShare_Market_News_17th_July_2026_TV5_Money", "youtube_url": "https://youtu.be/9kB6GkFpJGY"}, "weekly_digest": {"since": "2026-07-13", "lines": ["Kutumba Rao: 24 new buy calls — Heritage Foods, Ambuja Cements, Infosys, Capson, Pace Digitek …", "Kutumba Rao: 4 sells — IREDA, HUDCO, DAM Capital, Ganga [as heard]", "Kranthi: 12 new buy calls — Heritage Foods, Ather Energy, TVS Motors, Raymond, Raymond Realty …", "Kranthi: 1 sell — SW Solar (Sterling and Wilson)", "Most discussed: Biocon (2 mentions), Heritage Foods (2 mentions)"]}}